{
  "ItemType": 8,
  "Id": 282,
  "ShipId": 122,
  "DifficultyClass": 2,
  "Components": [
    {
      "ComponentId": 55,
      "Locked": true,
      "X": 4,
      "Y": 9,
      "BarrelId": -1
    },
    {
      "ComponentId": 55,
      "Locked": true,
      "X": 6,
      "Y": 9,
      "BarrelId": -1
    },
    {
      "ComponentId": 59,
      "Locked": true,
      "X": 5,
      "Y": 8,
      "BarrelId": -1
    },
    {
      "ComponentId": 59,
      "Locked": true,
      "X": 5,
      "Y": 11,
      "BarrelId": -1
    },
    {
      "ComponentId": 129,
      "Modification": 16,
      "Quality": 5,
      "Locked": true,
      "X": 4
    },
    {
      "ComponentId": 129,
      "Modification": 16,
      "Quality": 5,
      "Locked": true,
      "X": 6
    },
    {
      "ComponentId": 256,
      "Modification": 2,
      "Quality": 5,
      "Locked": true,
      "X": 5,
      "Y": 2,
      "BarrelId": -1,
      "KeyBinding": 1
    },
    {
      "ComponentId": 259,
      "Modification": 2,
      "Quality": 5,
      "Locked": true,
      "X": 3,
      "Y": 5,
      "BarrelId": -1,
      "KeyBinding": 2
    },
    {
      "ComponentId": 74,
      "Modification": 12,
      "Quality": 5,
      "Locked": true,
      "X": 6,
      "Y": 6,
      "BarrelId": -1,
      "KeyBinding": 3
    },
    {
      "ComponentId": 261,
      "Modification": 3,
      "Quality": 5,
      "Locked": true,
      "X": 8,
      "Y": 5,
      "BarrelId": -1,
      "KeyBinding": 3
    },
    {
      "ComponentId": 261,
      "Modification": 3,
      "Quality": 5,
      "Locked": true,
      "X": 8,
      "Y": 3,
      "BarrelId": -1,
      "KeyBinding": 3
    },
    {
      "ComponentId": 261,
      "Modification": 3,
      "Quality": 5,
      "Locked": true,
      "X": 2,
      "Y": 6,
      "BarrelId": -1,
      "KeyBinding": 3
    },
    {
      "ComponentId": 261,
      "Modification": 3,
      "Quality": 5,
      "Locked": true,
      "X": 2,
      "Y": 3,
      "BarrelId": -1,
      "KeyBinding": 3
    },
    {
      "ComponentId": 67,
      "Modification": 9,
      "Quality": 5,
      "Locked": true,
      "X": 4,
      "Y": 8,
      "BarrelId": -1,
      "KeyBinding": 3
    },
    {
      "ComponentId": 67,
      "Modification": 9,
      "Quality": 5,
      "Locked": true,
      "X": 6,
      "Y": 6,
      "BarrelId": -1,
      "KeyBinding": 3
    },
    {
      "ComponentId": 67,
      "Modification": 9,
      "Quality": 5,
      "Locked": true,
      "X": 7,
      "Y": 5,
      "BarrelId": -1,
      "KeyBinding": 3
    },
    {
      "ComponentId": 67,
      "Modification": 9,
      "Quality": 5,
      "Locked": true,
      "X": 6,
      "Y": 5,
      "BarrelId": -1,
      "KeyBinding": 3
    },
    {
      "ComponentId": 67,
      "Modification": 9,
      "Quality": 5,
      "Locked": true,
      "X": 4,
      "Y": 4,
      "BarrelId": -1,
      "KeyBinding": 3
    },
    {
      "ComponentId": 69,
      "Modification": 2,
      "Quality": 5,
      "Locked": true,
      "X": 4,
      "Y": 3,
      "BarrelId": -1,
      "KeyBinding": 3
    },
    {
      "ComponentId": 69,
      "Modification": 2,
      "Quality": 5,
      "Locked": true,
      "X": 4,
      "Y": 2,
      "BarrelId": -1,
      "KeyBinding": 3
    },
    {
      "ComponentId": 260,
      "Modification": 3,
      "Quality": 5,
      "Locked": true,
      "X": 8,
      "Y": 2,
      "BarrelId": -1,
      "KeyBinding": 3
    },
    {
      "ComponentId": 260,
      "Modification": 3,
      "Quality": 5,
      "Locked": true,
      "X": 8,
      "Y": 1,
      "BarrelId": -1,
      "KeyBinding": 3
    },
    {
      "ComponentId": 260,
      "Modification": 3,
      "Quality": 5,
      "Locked": true,
      "X": 9,
      "Y": 7,
      "BarrelId": -1,
      "KeyBinding": 3
    },
    {
      "ComponentId": 260,
      "Modification": 3,
      "Quality": 5,
      "Locked": true,
      "X": 2,
      "Y": 5,
      "BarrelId": -1,
      "KeyBinding": 3
    },
    {
      "ComponentId": 260,
      "Modification": 3,
      "Quality": 5,
      "Locked": true,
      "X": 3,
      "Y": 2,
      "BarrelId": -1,
      "KeyBinding": 3
    },
    {
      "ComponentId": 260,
      "Modification": 3,
      "Quality": 5,
      "Locked": true,
      "X": 3,
      "Y": 1,
      "BarrelId": -1,
      "KeyBinding": 3
    }
  ]
}