<?xml version="1.0" encoding="UTF-8"?>
<resources>
    <string name="Ship">Hajó</string>
    <string name="Satellite">Műhold</string>
    <string name="Device">Extra Felszerelés</string>
    <string name="DroneBay">Drónhangár</string>
    <string name="Weapon">Fegyver</string>
    <string name="Armor">Páncélzat</string>
    <string name="Reactor">Reaktor</string>
    <string name="Engine">Hajtómű</string>
    <string name="FuelTank">Energiatartály</string>
    <string name="WeightReduction">Súlycsökkentés</string>
    <string name="DroneBayCapacity">Kapacitás</string>
    <string name="DroneBayCooldown">Újratöltés</string>
    <string name="WeaponType">Fegyver</string>
    <string name="WeaponSlots">Fegyvercellák</string>
    <string name="CellCount">Méret</string>
    <string name="EngineSize">Hajtómű méret</string>
    <string name="Damage">Támadás</string>
    <string name="HitPoints">Életerő</string>
    <string name="Energy">Energia</string>
    <string name="ShieldPoints">Pajzspontok</string>
    <string name="ShieldRechargeRate">Pajzs regenerálódás</string>
    <string name="RepairRate">Javítási sebesség</string>
    <string name="RechargeRate">Energiatermelés</string>
    <string name="Weight">Súly</string>
    <string name="RamDamage">Ütközés sebzése</string>
    <string name="DamageAbsorption">Energiaelnyelés</string>
    <string name="Velocity">Sebesség</string>
    <string name="TurnRate">Fordulás</string>
    <string name="WeaponModifiers">Fegyver</string>
    <string name="DamageModifier">Sebzés</string>
    <string name="FireRateModifier">Tűzgyorsaság</string>
    <string name="RangeModifier">Tűztávolság</string>
    <string name="EnergyModifier">Energiahasználat</string>
    <string name="DroneDamageModifier">Drón sebzés</string>
    <string name="DroneRangeModifier">Drón hatótáv</string>
    <string name="DroneSpeedModifier">Drón sebesség</string>
    <string name="DroneDefenseModifier">Drón ellenállás</string>
    <string name="DroneReconstructionTime">Drón építési idő</string>
    <string name="KineticDamageResistance">Kinetikus ellenállás</string>
    <string name="ThermalDamageResistance">Hőellenállás</string>
    <string name="EnergyDamageResistance">Energia ellenállás</string>
    <string name="Size">Méret</string>
    <string name="EnergyConsumption">Energiahasználat</string>
    <string name="MenuWeapon">Támadás</string>
    <string name="MenuEnergy">Energia</string>
    <string name="MenuDefense">Védelem</string>
    <string name="MenuEngine">Meghajtás</string>
    <string name="MenuDrones">Drónok</string>
    <string name="MenuSpecial">Speciális</string>
    <string name="Exit">Kilép</string>
    <string name="AvailableSpace">Szabad hely: $1 / $2</string>
    <string name="MoreInfo">Több Infó</string>
    <string name="MinEnergy">Bekapcs, ha több mint $1% energia</string>
    <string name="Automatic">Automatikus</string>
    <string name="KeyBinding">Akciógomb</string>
    <string name="DroneBehaviour">Viselkedés:</string>
    <string name="RequiredCell">Cellatípus</string>
    <string name="PressToInstall">Húzd a telepítéshez</string>
    <string name="NotEnoughSpace">Nincs elég hely</string>
    <string name="AlreadyInstalled">Ilyen modul már telepítve van</string>
    <string name="CannotInstall">A modul nem kompatibilis ezzel a hajóval</string>
    <string name="ShowDetails">Részletek mutatása</string>
    <string name="RemoveComponent">Eltávolít</string>
    <string name="UnlockComponent">Felold</string>
    <string name="UnlockAllComponents">Mindet Felold</string>
    <string name="UnlockConfirmation">Kiválasztott modul feloldása?</string>
    <string name="UnlockAllConfirmation">Minden kötött modul feloldása?</string>
    <string name="RequiredSpaceText">Szükséges üres hely: $1</string>
    <string name="OutOfSpaceWarning">Nincs elég üres hely. Szabadíts fel $1 ${1|cellát|cellát} vagy növeld a hajó szintjét.</string>
    <string name="LowLevelText">A hajódnak $1 vagy nagyobb szintűnek kell lennie.</string>
    <string name="LowLevelUnlockText">A modul feloldásához a hajódnak $1 vagy nagyobb szintűnek kell lennie.</string>
    <string name="UnknownTech">Ismeretlen technológia. Előbb fejleszd ki.</string>
    <string name="RemoveAllConfirmation">Minden telepített modul eltávolítása?</string>
    <string name="WeaponDamage">Sebzés</string>
    <string name="WeaponDPS">Sebzés másodpercenként</string>
    <string name="WeaponEnergy">Energiahasználat</string>
    <string name="WeaponEPS">Energia másodpercenként</string>
    <string name="WeaponRange">Lőtáv</string>
    <string name="WeaponCooldown">Újratöltés</string>
    <string name="WeaponVelocity">Sebesség</string>
    <string name="WeaponArea">Hatóterület</string>
    <string name="WeaponImpulse">Impulzus</string>
    <string name="DamageType">Sebzéstípus</string>
    <string name="ImpactDamage">Kinetikus</string>
    <string name="EnergyDamage">Energia</string>
    <string name="HeatDamage">Hő</string>
    <string name="ShipName">Hajó neve</string>
    <string name="ClickToInstall">Telepítéshez kattints</string>
    <string name="ClickToRemove">Eltávolításhoz kattints</string>
    <string name="CantBeInstalled">Nem lehet telepíteni</string>
    <string name="LeftSide">Bal</string>
    <string name="RightSide">Jobb</string>
    <string name="LockedSlot">Hangár nem elérhető. Oldd fel a képességfán.</string>
    <string name="EmptySlot0">Üres hangár fregattoknak</string>
    <string name="EmptySlot1">Üres hangár rombolóknak</string>
    <string name="EmptySlot2">Üres hangár cirkálóknak</string>
    <string name="EmptySlot3">Üres hangár csatahajóknak</string>
    <string name="EmptySlot4">Üres hangár zászlóshajóknak</string>
    <string name="ShipClass">Osztály:</string>
    <string name="ClassFrigate">Fregatt</string>
    <string name="ClassDestroyer">Romboló</string>
    <string name="ClassCruiser">Cirkáló</string>
    <string name="ClassBattleship">Csatahajó</string>
    <string name="ClassTitan">Zászlóshajó</string>
    <string name="GroupAll">Minden modul</string>
    <string name="GroupWeapon">Fegyverek</string>
    <string name="GroupArmor">Védelmi modulok</string>
    <string name="GroupEngines">Hajtóművek</string>
    <string name="GroupEnergy">Energiamodulok</string>
    <string name="GroupDrones">Drónok</string>
    <string name="GroupSpecial">Speciális modulok</string>
    <string name="GroupShip">$1 hajómodul</string>
    <string name="GroupShips">Hajók</string>
    <string name="GroupWeaponAny">Szabad típusú fegyverek</string>
    <string name="GroupWeaponC">Lövedék fegyverek</string>
    <string name="GroupWeaponL">Sugárfegyverek</string>
    <string name="GroupWeaponM">Rakéták</string>
    <string name="GroupWeaponT">Torpedók</string>
    <string name="GroupWeaponS">Speciális fegyverek</string>
</resources>
